LICENSE
README.md
setup.py
colab_vgradio_codex/__init__.py
colab_vgradio_codex/app.py
colab_vgradio_codex/auth.py
colab_vgradio_codex/email_utils.py
colab_vgradio_codex/fragment.py
colab_vgradio_codex/image2_to_reference.py
colab_vgradio_codex/image2_to_video.py
colab_vgradio_codex/image2_to_video10.py
colab_vgradio_codex/image3_to_reference.py
colab_vgradio_codex/image3_to_video.py
colab_vgradio_codex/image_to_reference.py
colab_vgradio_codex/image_to_reference_10.py
colab_vgradio_codex/image_to_video_10.py
colab_vgradio_codex/image_to_video_15_20.py
colab_vgradio_codex/main.py
colab_vgradio_codex/render.py
colab_vgradio_codex/text_to_video_10.py
colab_vgradio_codex/text_to_video_15_20.py
colab_vgradio_codex/text_to_video_15_201.py
colab_vgradio_codex/upload_pic.py
colab_vgradio_codex/upscalers.py
colab_vgradio_codex/utils.py
colab_vgradio_codex/vidu_credit.py
colab_vgradio_codex.egg-info/PKG-INFO
colab_vgradio_codex.egg-info/SOURCES.txt
colab_vgradio_codex.egg-info/dependency_links.txt
colab_vgradio_codex.egg-info/requires.txt
colab_vgradio_codex.egg-info/top_level.txt